keyboard_switch/__init__.py
keyboard_switch/kbswitch.py
keyboard_switch-0.1.3.dist-info/LICENSE
keyboard_switch-0.1.3.dist-info/METADATA
keyboard_switch-0.1.3.dist-info/WHEEL
keyboard_switch-0.1.3.dist-info/entry_points.txt
keyboard_switch-0.1.3.dist-info/top_level.txt
keyboard_switch-0.1.3.dist-info/RECORD
