Metadata-Version: 2.1
Name: keyboard-switch
Version: 0.1.3
Summary: Simple script written in Python to change keyboard layout on linux by using setxkbmap.
Home-page: https://github.com/firgaty/keyboard-switch
Author: Félix Desmaretz
Author-email: felix.desmaretz@protonmail.com
License: UNKNOWN
Platform: UNKNOWN
Classifier: Programming Language :: Python :: 3
Classifier: License :: OSI Approved :: Mozilla Public License 2.0 (MPL 2.0)
Classifier: Operating System :: POSIX :: Linux
Requires-Python: >=3.6
